social_net_img_classifier/__init__.py
social_net_img_classifier/aws_utils.py
social_net_img_classifier/classify.py
social_net_img_classifier/data/alcohorithm-dm-templates.json
social_net_img_classifier/data/alcohorithm-response-templates.json
social_net_img_classifier/data/cities_table.csv
social_net_img_classifier/data/countries_table.csv
social_net_img_classifier/data/locations_co.json
social_net_img_classifier/data/names_gender.csv
social_net_img_classifier/data/prompt_gpt3_moments.txt
social_net_img_classifier/db_tools.py
social_net_img_classifier/etl.py
social_net_img_classifier/models/model.h5
social_net_img_classifier/models/text_model.h5
social_net_img_classifier/nudeclf.py
social_net_img_classifier/settings.py
social_net_img_classifier/training.py
social_net_img_classifier/utils.py
social_net_img_classifier-0.6.1.dist-info/METADATA
social_net_img_classifier-0.6.1.dist-info/WHEEL
social_net_img_classifier-0.6.1.dist-info/RECORD
