Metadata-Version: 2.1
Name: social-net-img-classifier
Version: 0.6.1
Summary: 
Author: Gabriel
Author-email: gabriel@whaleandjaguar.co
Requires-Python: >=3.8,<3.10
Classifier: Programming Language :: Python :: 3
Classifier: Programming Language :: Python :: 3.8
Classifier: Programming Language :: Python :: 3.9
Requires-Dist: Pillow (==9.1.1)
Requires-Dist: PyMySQL (==1.0.2)
Requires-Dist: bertopic (==0.12.0)
Requires-Dist: boto3 (>=1.25.1,<2.0.0)
Requires-Dist: fuzzywuzzy (==0.18.0)
Requires-Dist: imblearn (>=0.0,<0.1)
Requires-Dist: keras (==2.9.0)
Requires-Dist: langid (==1.1.6)
Requires-Dist: lightgbm (==3.3.2)
Requires-Dist: nltk (==3.7)
Requires-Dist: numpy (==1.21.3)
Requires-Dist: onnxruntime (==1.12.0)
Requires-Dist: openai (==0.25.0)
Requires-Dist: optuna (==2.10.1)
Requires-Dist: pandas (==1.3.2)
Requires-Dist: python-Levenshtein (==0.20.5)
Requires-Dist: requests (>=2.28.1,<3.0.0)
Requires-Dist: reverse_geocoder (==1.5.1)
Requires-Dist: scikit-learn (==1.1.1)
Requires-Dist: simpletransformers (==0.63.7)
Requires-Dist: six (==1.16.0)
Requires-Dist: spacy (==3.4.1)
Requires-Dist: tensorflow (>=2.1.0rc0,<3.0.0)
Requires-Dist: torch (==1.10.1)
Requires-Dist: transformers (==4.20.1)
Requires-Dist: wj-social-net-queries (>=0.15.0,<0.16.0)
